{
  "aliases": [],
  "api_docs_html": "",
  "area": "stats",
  "body_sections": [
    {
      "blocks": [
        {
          "inline": [
            {
              "kind": "text",
              "text": "Percent-point function (inverse CDF) at "
            },
            {
              "kind": "emphasis",
              "text": "q"
            },
            {
              "kind": "text",
              "text": "."
            }
          ],
          "type": "paragraph"
        }
      ],
      "title": "Summary"
    },
    {
      "blocks": [
        {
          "inline": [
            {
              "kind": "text",
              "text": "Equivalent to "
            },
            {
              "external_url": "https://docs.scipy.org/doc/scipy/reference/generated/scipy.stats.cauchy.ppf(q, loc, scale).html",
              "href": "",
              "kind": "link",
              "target": "stats.cauchy.ppf(q, loc, scale)",
              "text": "scipy.stats.cauchy.ppf(q, loc, scale)"
            },
            {
              "kind": "text",
              "text": "."
            }
          ],
          "type": "paragraph"
        }
      ],
      "title": "Extended Summary"
    }
  ],
  "canonical_name": "stats.cauchy.ppf",
  "category": "counted_custom",
  "cost_formula": "5n",
  "cost_formula_latex": "$5n$",
  "display_type": "custom",
  "doc_coverage": {
    "raw_blocks": [],
    "unresolved_references": [],
    "unsupported_directives": []
  },
  "example": null,
  "href": "/docs/api/ops/stats-cauchy-ppf/",
  "module": "whest.stats",
  "name": "stats.cauchy.ppf",
  "next": {
    "href": "/docs/api/ops/stats-expon-cdf/",
    "label": "we.stats.expon.cdf"
  },
  "notes": "Cauchy PPF; cost = numel(input).",
  "notes_sections": [],
  "numpy_ref": "np.stats.cauchy.ppf",
  "parameters": [],
  "previous": {
    "href": "/docs/api/ops/stats-cauchy-pdf/",
    "label": "we.stats.cauchy.pdf"
  },
  "provenance_label": "Adapted from NumPy docs",
  "provenance_url": "https://docs.scipy.org/doc/scipy/reference/generated/scipy.stats.cauchy.html",
  "returns": [],
  "see_also": [],
  "signature": "we.stats.cauchy.ppf(q, loc=0, scale=1)",
  "slug": "stats-cauchy-ppf",
  "summary": "Percent-point function (inverse CDF) at *q*.",
  "upstream_source_url": "",
  "weight": 16.0,
  "whest_examples_html": "",
  "whest_ref": "we.stats.cauchy.ppf",
  "whest_source_url": "https://github.com/AIcrowd/whest/blob/main/src/whest/stats/_cauchy.py#L54"
}
