{
  "detail_href": "/docs/api/ops/in1d/",
  "detail_json_href": "/api-data/ops/in1d.json",
  "docs": {
    "sections": []
  },
  "op": {
    "category": "counted_custom",
    "cost_formula": "per-operation",
    "cost_formula_latex": "varies",
    "flopscope_ref": "fnp.in1d",
    "module": "numpy",
    "name": "in1d",
    "notes": "Set membership; cost = (n+m)*ceil(log2(n+m)). Removed in numpy 2.4; use `isin` instead.",
    "numpy_ref": "np.in1d",
    "signature": "fnp.in1d(*args, **kwargs)",
    "status": "supported",
    "summary": "",
    "weight": 1.0
  },
  "schema_version": 1,
  "slug": "in1d",
  "source": {
    "flopscope": "https://github.com/AIcrowd/flopscope/blob/main/src/flopscope/_sorting_ops.py#L386",
    "numpy": "https://numpy.org/doc/stable/reference/generated/numpy.in1d.html"
  }
}
