{
  "aliases": [
    "fnp.set_printoptions"
  ],
  "area": "numpy",
  "body_sections": [
    {
      "blocks": [
        {
          "inline": [
            {
              "kind": "text",
              "text": "Set printing options."
            }
          ],
          "type": "paragraph"
        }
      ],
      "title": "Summary"
    },
    {
      "blocks": [
        {
          "inline": [
            {
              "kind": "text",
              "text": "These options determine the way floating point numbers, arrays and\nother NumPy objects are displayed."
            }
          ],
          "type": "paragraph"
        }
      ],
      "title": "Extended Summary"
    },
    {
      "blocks": [
        {
          "items": [
            {
              "body_blocks": [
                {
                  "inline": [
                    {
                      "kind": "text",
                      "text": "Number of digits of precision for floating point output (default 8).\nMay be None if "
                    },
                    {
                      "kind": "code",
                      "text": "floatmode"
                    },
                    {
                      "kind": "text",
                      "text": " is not "
                    },
                    {
                      "kind": "code",
                      "text": "fixed"
                    },
                    {
                      "kind": "text",
                      "text": ", to print as many digits as\nnecessary to uniquely specify the value."
                    }
                  ],
                  "type": "paragraph"
                }
              ],
              "data_type": "int or None, optional",
              "inline": [
                {
                  "kind": "text",
                  "text": "Number of digits of precision for floating point output (default 8).\nMay be None if "
                },
                {
                  "kind": "code",
                  "text": "floatmode"
                },
                {
                  "kind": "text",
                  "text": " is not "
                },
                {
                  "kind": "code",
                  "text": "fixed"
                },
                {
                  "kind": "text",
                  "text": ", to print as many digits as\nnecessary to uniquely specify the value."
                }
              ],
              "name": "precision",
              "type": "field_list"
            },
            {
              "body_blocks": [
                {
                  "inline": [
                    {
                      "kind": "text",
                      "text": "Total number of array elements which trigger summarization\nrather than full repr (default 1000).\nTo always use the full repr without summarization, pass "
                    },
                    {
                      "kind": "code",
                      "text": "sys.maxsize"
                    },
                    {
                      "kind": "text",
                      "text": "."
                    }
                  ],
                  "type": "paragraph"
                }
              ],
              "data_type": "int, optional",
              "inline": [
                {
                  "kind": "text",
                  "text": "Total number of array elements which trigger summarization\nrather than full repr (default 1000).\nTo always use the full repr without summarization, pass "
                },
                {
                  "kind": "code",
                  "text": "sys.maxsize"
                },
                {
                  "kind": "text",
                  "text": "."
                }
              ],
              "name": "threshold",
              "type": "field_list"
            },
            {
              "body_blocks": [
                {
                  "inline": [
                    {
                      "kind": "text",
                      "text": "Number of array items in summary at beginning and end of\neach dimension (default 3)."
                    }
                  ],
                  "type": "paragraph"
                }
              ],
              "data_type": "int, optional",
              "inline": [
                {
                  "kind": "text",
                  "text": "Number of array items in summary at beginning and end of\neach dimension (default 3)."
                }
              ],
              "name": "edgeitems",
              "type": "field_list"
            },
            {
              "body_blocks": [
                {
                  "inline": [
                    {
                      "kind": "text",
                      "text": "The number of characters per line for the purpose of inserting\nline breaks (default 75)."
                    }
                  ],
                  "type": "paragraph"
                }
              ],
              "data_type": "int, optional",
              "inline": [
                {
                  "kind": "text",
                  "text": "The number of characters per line for the purpose of inserting\nline breaks (default 75)."
                }
              ],
              "name": "linewidth",
              "type": "field_list"
            },
            {
              "body_blocks": [
                {
                  "inline": [
                    {
                      "kind": "text",
                      "text": "If True, always print floating point numbers using fixed point\nnotation, in which case numbers equal to zero in the current precision\nwill print as zero.  If False, then scientific notation is used when\nabsolute value of the smallest number is < 1e-4 or the ratio of the\nmaximum absolute value to the minimum is > 1e3. The default is False."
                    }
                  ],
                  "type": "paragraph"
                }
              ],
              "data_type": "bool, optional",
              "inline": [
                {
                  "kind": "text",
                  "text": "If True, always print floating point numbers using fixed point\nnotation, in which case numbers equal to zero in the current precision\nwill print as zero.  If False, then scientific notation is used when\nabsolute value of the smallest number is < 1e-4 or the ratio of the\nmaximum absolute value to the minimum is > 1e3. The default is False."
                }
              ],
              "name": "suppress",
              "type": "field_list"
            },
            {
              "body_blocks": [
                {
                  "inline": [
                    {
                      "kind": "text",
                      "text": "String representation of floating point not-a-number (default nan)."
                    }
                  ],
                  "type": "paragraph"
                }
              ],
              "data_type": "str, optional",
              "inline": [
                {
                  "kind": "text",
                  "text": "String representation of floating point not-a-number (default nan)."
                }
              ],
              "name": "nanstr",
              "type": "field_list"
            },
            {
              "body_blocks": [
                {
                  "inline": [
                    {
                      "kind": "text",
                      "text": "String representation of floating point infinity (default inf)."
                    }
                  ],
                  "type": "paragraph"
                }
              ],
              "data_type": "str, optional",
              "inline": [
                {
                  "kind": "text",
                  "text": "String representation of floating point infinity (default inf)."
                }
              ],
              "name": "infstr",
              "type": "field_list"
            },
            {
              "body_blocks": [
                {
                  "inline": [
                    {
                      "kind": "text",
                      "text": "Controls printing of the sign of floating-point types. If '+', always\nprint the sign of positive values. If ' ', always prints a space\n(whitespace character) in the sign position of positive values.  If\n'-', omit the sign character of positive values. (default '-')"
                    }
                  ],
                  "type": "paragraph"
                },
                {
                  "argument_inline": [],
                  "content_blocks": [],
                  "directive": "versionchanged",
                  "options": [],
                  "raw_source": ".. versionchanged:: 2.0\n     The sign parameter can now be an integer type, previously\n     types were floating-point types.",
                  "supported": true,
                  "type": "directive_block",
                  "version": "2.0"
                }
              ],
              "data_type": "string, either '-', '+', or ' ', optional",
              "inline": [
                {
                  "kind": "text",
                  "text": "Controls printing of the sign of floating-point types. If '+', always\nprint the sign of positive values. If ' ', always prints a space\n(whitespace character) in the sign position of positive values.  If\n'-', omit the sign character of positive values. (default '-')"
                }
              ],
              "name": "sign",
              "type": "field_list"
            },
            {
              "body_blocks": [
                {
                  "inline": [
                    {
                      "kind": "text",
                      "text": "If not None, the keys should indicate the type(s) that the respective\nformatting function applies to.  Callables should return a string.\nTypes that are not specified (by their corresponding keys) are handled\nby the default formatters.  Individual types for which a formatter\ncan be set are:"
                    }
                  ],
                  "type": "paragraph"
                },
                {
                  "items": [
                    {
                      "blocks": [
                        {
                          "inline": [
                            {
                              "kind": "text",
                              "text": "'bool'"
                            }
                          ],
                          "type": "paragraph"
                        }
                      ]
                    },
                    {
                      "blocks": [
                        {
                          "inline": [
                            {
                              "kind": "text",
                              "text": "'int'"
                            }
                          ],
                          "type": "paragraph"
                        }
                      ]
                    },
                    {
                      "blocks": [
                        {
                          "inline": [
                            {
                              "kind": "text",
                              "text": "'timedelta' : a "
                            },
                            {
                              "external_url": "https://numpy.org/doc/stable/reference/generated/numpy.timedelta64.html",
                              "href": "",
                              "kind": "link",
                              "target": "timedelta64",
                              "text": "flops.timedelta64"
                            }
                          ],
                          "type": "paragraph"
                        }
                      ]
                    },
                    {
                      "blocks": [
                        {
                          "inline": [
                            {
                              "kind": "text",
                              "text": "'datetime' : a "
                            },
                            {
                              "external_url": "https://numpy.org/doc/stable/reference/generated/numpy.datetime64.html",
                              "href": "",
                              "kind": "link",
                              "target": "datetime64",
                              "text": "flops.datetime64"
                            }
                          ],
                          "type": "paragraph"
                        }
                      ]
                    },
                    {
                      "blocks": [
                        {
                          "inline": [
                            {
                              "kind": "text",
                              "text": "'float'"
                            }
                          ],
                          "type": "paragraph"
                        }
                      ]
                    },
                    {
                      "blocks": [
                        {
                          "inline": [
                            {
                              "kind": "text",
                              "text": "'longfloat' : 128-bit floats"
                            }
                          ],
                          "type": "paragraph"
                        }
                      ]
                    },
                    {
                      "blocks": [
                        {
                          "inline": [
                            {
                              "kind": "text",
                              "text": "'complexfloat'"
                            }
                          ],
                          "type": "paragraph"
                        }
                      ]
                    },
                    {
                      "blocks": [
                        {
                          "inline": [
                            {
                              "kind": "text",
                              "text": "'longcomplexfloat' : composed of two 128-bit floats"
                            }
                          ],
                          "type": "paragraph"
                        }
                      ]
                    },
                    {
                      "blocks": [
                        {
                          "inline": [
                            {
                              "kind": "text",
                              "text": "'numpystr' : types "
                            },
                            {
                              "external_url": "https://numpy.org/doc/stable/reference/generated/numpy.bytes_.html",
                              "href": "",
                              "kind": "link",
                              "target": "bytes_",
                              "text": "flops.bytes_"
                            },
                            {
                              "kind": "text",
                              "text": " and "
                            },
                            {
                              "external_url": "https://numpy.org/doc/stable/reference/generated/numpy.str_.html",
                              "href": "",
                              "kind": "link",
                              "target": "str_",
                              "text": "flops.str_"
                            }
                          ],
                          "type": "paragraph"
                        }
                      ]
                    },
                    {
                      "blocks": [
                        {
                          "inline": [
                            {
                              "kind": "text",
                              "text": "'object' : "
                            },
                            {
                              "external_url": "https://numpy.org/doc/stable/reference/generated/numpy.object_.html",
                              "href": "",
                              "kind": "link",
                              "target": "object_",
                              "text": "flops.object_"
                            },
                            {
                              "kind": "text",
                              "text": " arrays"
                            }
                          ],
                          "type": "paragraph"
                        }
                      ]
                    }
                  ],
                  "ordered": false,
                  "type": "list"
                },
                {
                  "inline": [
                    {
                      "kind": "text",
                      "text": "Other keys that can be used to set a group of types at once are:"
                    }
                  ],
                  "type": "paragraph"
                },
                {
                  "items": [
                    {
                      "blocks": [
                        {
                          "inline": [
                            {
                              "kind": "text",
                              "text": "'all' : sets all types"
                            }
                          ],
                          "type": "paragraph"
                        }
                      ]
                    },
                    {
                      "blocks": [
                        {
                          "inline": [
                            {
                              "kind": "text",
                              "text": "'int_kind' : sets 'int'"
                            }
                          ],
                          "type": "paragraph"
                        }
                      ]
                    },
                    {
                      "blocks": [
                        {
                          "inline": [
                            {
                              "kind": "text",
                              "text": "'float_kind' : sets 'float' and 'longfloat'"
                            }
                          ],
                          "type": "paragraph"
                        }
                      ]
                    },
                    {
                      "blocks": [
                        {
                          "inline": [
                            {
                              "kind": "text",
                              "text": "'complex_kind' : sets 'complexfloat' and 'longcomplexfloat'"
                            }
                          ],
                          "type": "paragraph"
                        }
                      ]
                    },
                    {
                      "blocks": [
                        {
                          "inline": [
                            {
                              "kind": "text",
                              "text": "'str_kind' : sets 'numpystr'"
                            }
                          ],
                          "type": "paragraph"
                        }
                      ]
                    }
                  ],
                  "ordered": false,
                  "type": "list"
                }
              ],
              "data_type": "dict of callables, optional",
              "inline": [
                {
                  "kind": "text",
                  "text": "If not None, the keys should indicate the type(s) that the respective\nformatting function applies to.  Callables should return a string.\nTypes that are not specified (by their corresponding keys) are handled\nby the default formatters.  Individual types for which a formatter\ncan be set are:"
                }
              ],
              "name": "formatter",
              "type": "field_list"
            },
            {
              "body_blocks": [
                {
                  "inline": [
                    {
                      "kind": "text",
                      "text": "Controls the interpretation of the "
                    },
                    {
                      "kind": "code",
                      "text": "precision"
                    },
                    {
                      "kind": "text",
                      "text": " option for\nfloating-point types. Can take the following values\n(default maxprec_equal):"
                    }
                  ],
                  "type": "paragraph"
                },
                {
                  "items": [
                    {
                      "blocks": [
                        {
                          "items": [
                            {
                              "blocks": [
                                {
                                  "inline": [
                                    {
                                      "kind": "text",
                                      "text": "even if this would print more or fewer digits than\nnecessary to specify the value uniquely."
                                    }
                                  ],
                                  "type": "paragraph"
                                }
                              ],
                              "term_inline": [
                                {
                                  "kind": "text",
                                  "text": "'fixed': Always print exactly "
                                },
                                {
                                  "kind": "code",
                                  "text": "precision"
                                },
                                {
                                  "kind": "text",
                                  "text": " fractional digits,"
                                }
                              ]
                            }
                          ],
                          "type": "definition_list"
                        }
                      ]
                    },
                    {
                      "blocks": [
                        {
                          "items": [
                            {
                              "blocks": [
                                {
                                  "inline": [
                                    {
                                      "kind": "text",
                                      "text": "to represent each value uniquely. Different elements may\nhave a different number of digits. The value of the\n"
                                    },
                                    {
                                      "kind": "code",
                                      "text": "precision"
                                    },
                                    {
                                      "kind": "text",
                                      "text": " option is ignored."
                                    }
                                  ],
                                  "type": "paragraph"
                                }
                              ],
                              "term_inline": [
                                {
                                  "kind": "text",
                                  "text": "'unique': Print the minimum number of fractional digits necessary"
                                }
                              ]
                            }
                          ],
                          "type": "definition_list"
                        }
                      ]
                    },
                    {
                      "blocks": [
                        {
                          "items": [
                            {
                              "blocks": [
                                {
                                  "inline": [
                                    {
                                      "kind": "text",
                                      "text": "an element can be uniquely represented with fewer digits\nonly print it with that many."
                                    }
                                  ],
                                  "type": "paragraph"
                                }
                              ],
                              "term_inline": [
                                {
                                  "kind": "text",
                                  "text": "'maxprec': Print at most "
                                },
                                {
                                  "kind": "code",
                                  "text": "precision"
                                },
                                {
                                  "kind": "text",
                                  "text": " fractional digits, but if"
                                }
                              ]
                            }
                          ],
                          "type": "definition_list"
                        }
                      ]
                    },
                    {
                      "blocks": [
                        {
                          "items": [
                            {
                              "blocks": [
                                {
                                  "inline": [
                                    {
                                      "kind": "text",
                                      "text": "but if every element in the array can be uniquely\nrepresented with an equal number of fewer digits, use that\nmany digits for all elements."
                                    }
                                  ],
                                  "type": "paragraph"
                                }
                              ],
                              "term_inline": [
                                {
                                  "kind": "text",
                                  "text": "'maxprec_equal': Print at most "
                                },
                                {
                                  "kind": "code",
                                  "text": "precision"
                                },
                                {
                                  "kind": "text",
                                  "text": " fractional digits,"
                                }
                              ]
                            }
                          ],
                          "type": "definition_list"
                        }
                      ]
                    }
                  ],
                  "ordered": false,
                  "type": "list"
                }
              ],
              "data_type": "str, optional",
              "inline": [
                {
                  "kind": "text",
                  "text": "Controls the interpretation of the "
                },
                {
                  "kind": "code",
                  "text": "precision"
                },
                {
                  "kind": "text",
                  "text": " option for\nfloating-point types. Can take the following values\n(default maxprec_equal):"
                }
              ],
              "name": "floatmode",
              "type": "field_list"
            },
            {
              "body_blocks": [
                {
                  "inline": [
                    {
                      "kind": "text",
                      "text": "If set to the string "
                    },
                    {
                      "kind": "code",
                      "text": "'1.13'"
                    },
                    {
                      "kind": "text",
                      "text": " enables 1.13 legacy printing mode. This\napproximates numpy 1.13 print output by including a space in the sign\nposition of floats and different behavior for 0d arrays. This also\nenables 1.21 legacy printing mode (described below)."
                    }
                  ],
                  "type": "paragraph"
                },
                {
                  "inline": [
                    {
                      "kind": "text",
                      "text": "If set to the string "
                    },
                    {
                      "kind": "code",
                      "text": "'1.21'"
                    },
                    {
                      "kind": "text",
                      "text": " enables 1.21 legacy printing mode. This\napproximates numpy 1.21 print output of complex structured dtypes\nby not inserting spaces after commas that separate fields and after\ncolons."
                    }
                  ],
                  "type": "paragraph"
                },
                {
                  "inline": [
                    {
                      "kind": "text",
                      "text": "If set to "
                    },
                    {
                      "kind": "code",
                      "text": "'1.25'"
                    },
                    {
                      "kind": "text",
                      "text": " approximates printing of 1.25 which mainly means\nthat numeric scalars are printed without their type information, e.g.\nas "
                    },
                    {
                      "kind": "code",
                      "text": "3.0"
                    },
                    {
                      "kind": "text",
                      "text": " rather than "
                    },
                    {
                      "kind": "code",
                      "text": "flops.float64(3.0)"
                    },
                    {
                      "kind": "text",
                      "text": "."
                    }
                  ],
                  "type": "paragraph"
                },
                {
                  "inline": [
                    {
                      "kind": "text",
                      "text": "If set to "
                    },
                    {
                      "kind": "code",
                      "text": "'2.1'"
                    },
                    {
                      "kind": "text",
                      "text": ", shape information is not given when arrays are\nsummarized (i.e., multiple elements replaced with "
                    },
                    {
                      "kind": "code",
                      "text": "..."
                    },
                    {
                      "kind": "text",
                      "text": ")."
                    }
                  ],
                  "type": "paragraph"
                },
                {
                  "inline": [
                    {
                      "kind": "text",
                      "text": "If set to "
                    },
                    {
                      "kind": "code",
                      "text": "False"
                    },
                    {
                      "kind": "text",
                      "text": ", disables legacy mode."
                    }
                  ],
                  "type": "paragraph"
                },
                {
                  "inline": [
                    {
                      "kind": "text",
                      "text": "Unrecognized strings will be ignored with a warning for forward\ncompatibility."
                    }
                  ],
                  "type": "paragraph"
                },
                {
                  "argument_inline": [],
                  "content_blocks": [],
                  "directive": "versionchanged",
                  "options": [],
                  "raw_source": ".. versionchanged:: 1.22.0",
                  "supported": true,
                  "type": "directive_block",
                  "version": "1.22.0"
                },
                {
                  "argument_inline": [],
                  "content_blocks": [],
                  "directive": "versionchanged",
                  "options": [],
                  "raw_source": ".. versionchanged:: 2.2",
                  "supported": true,
                  "type": "directive_block",
                  "version": "2.2"
                }
              ],
              "data_type": "string or `False`, optional",
              "inline": [
                {
                  "kind": "text",
                  "text": "If set to the string "
                },
                {
                  "kind": "code",
                  "text": "'1.13'"
                },
                {
                  "kind": "text",
                  "text": " enables 1.13 legacy printing mode. This\napproximates numpy 1.13 print output by including a space in the sign\nposition of floats and different behavior for 0d arrays. This also\nenables 1.21 legacy printing mode (described below)."
                }
              ],
              "name": "legacy",
              "type": "field_list"
            },
            {
              "body_blocks": [
                {
                  "inline": [
                    {
                      "kind": "text",
                      "text": "If set a passed function will be used for generating arrays' repr.\nOther options will be ignored."
                    }
                  ],
                  "type": "paragraph"
                }
              ],
              "data_type": "",
              "inline": [
                {
                  "kind": "text",
                  "text": "If set a passed function will be used for generating arrays' repr.\nOther options will be ignored."
                }
              ],
              "name": "override_repr: callable, optional",
              "type": "field_list"
            }
          ],
          "title": "Parameters",
          "type": "field_list"
        }
      ],
      "title": "Parameters"
    },
    {
      "blocks": [
        {
          "links": [
            {
              "description": "",
              "description_inline": [],
              "external_url": "https://numpy.org/doc/stable/reference/generated/numpy.get_printoptions.html",
              "href": "",
              "label": "get_printoptions",
              "original_target": "get_printoptions",
              "role": "",
              "target": "get_printoptions",
              "unresolved": false
            },
            {
              "description": "",
              "description_inline": [],
              "external_url": "https://numpy.org/doc/stable/reference/generated/numpy.printoptions.html",
              "href": "",
              "label": "printoptions",
              "original_target": "printoptions",
              "role": "",
              "target": "printoptions",
              "unresolved": false
            },
            {
              "description": "",
              "description_inline": [],
              "external_url": "https://numpy.org/doc/stable/reference/generated/numpy.array2string.html",
              "href": "",
              "label": "array2string",
              "original_target": "array2string",
              "role": "",
              "target": "array2string",
              "unresolved": false
            }
          ],
          "type": "link_list"
        }
      ],
      "title": "See also"
    },
    {
      "blocks": [
        {
          "inline": [
            {
              "kind": "code",
              "text": "formatter"
            },
            {
              "kind": "text",
              "text": " is always reset with a call to "
            },
            {
              "kind": "code",
              "text": "set_printoptions"
            },
            {
              "kind": "text",
              "text": "."
            }
          ],
          "type": "paragraph"
        },
        {
          "inline": [
            {
              "kind": "text",
              "text": "Use "
            },
            {
              "kind": "code",
              "text": "printoptions"
            },
            {
              "kind": "text",
              "text": " as a context manager to set the values temporarily."
            }
          ],
          "type": "paragraph"
        }
      ],
      "title": "Notes"
    },
    {
      "blocks": [
        {
          "inline": [
            {
              "kind": "text",
              "text": "Floating point precision can be set:"
            }
          ],
          "type": "paragraph"
        },
        {
          "lines": [
            {
              "kind": "input",
              "prompt": ">>>",
              "text": "import flopscope.numpy as fnp"
            },
            {
              "kind": "input",
              "prompt": ">>>",
              "text": "flops.set_printoptions(precision=4)"
            },
            {
              "kind": "input",
              "prompt": ">>>",
              "text": "flops.array([1.123456789])"
            },
            {
              "kind": "output",
              "text": "[1.1235]"
            }
          ],
          "type": "doctest_block"
        },
        {
          "inline": [
            {
              "kind": "text",
              "text": "Long arrays can be summarised:"
            }
          ],
          "type": "paragraph"
        },
        {
          "lines": [
            {
              "kind": "input",
              "prompt": ">>>",
              "text": "flops.set_printoptions(threshold=5)"
            },
            {
              "kind": "input",
              "prompt": ">>>",
              "text": "flops.arange(10)"
            },
            {
              "kind": "output",
              "text": "array([0, 1, 2, ..., 7, 8, 9], shape=(10,))"
            }
          ],
          "type": "doctest_block"
        },
        {
          "inline": [
            {
              "kind": "text",
              "text": "Small results can be suppressed:"
            }
          ],
          "type": "paragraph"
        },
        {
          "lines": [
            {
              "kind": "input",
              "prompt": ">>>",
              "text": "eps = flops.finfo(float).eps"
            },
            {
              "kind": "input",
              "prompt": ">>>",
              "text": "x = flops.arange(4.)"
            },
            {
              "kind": "input",
              "prompt": ">>>",
              "text": "x**2 - (x + eps)**2"
            },
            {
              "kind": "output",
              "text": "array([-4.9304e-32, -4.4409e-16,  0.0000e+00,  0.0000e+00])"
            },
            {
              "kind": "input",
              "prompt": ">>>",
              "text": "flops.set_printoptions(suppress=True)"
            },
            {
              "kind": "input",
              "prompt": ">>>",
              "text": "x**2 - (x + eps)**2"
            },
            {
              "kind": "output",
              "text": "array([-0., -0.,  0.,  0.])"
            }
          ],
          "type": "doctest_block"
        },
        {
          "inline": [
            {
              "kind": "text",
              "text": "A custom formatter can be used to display array elements as desired:"
            }
          ],
          "type": "paragraph"
        },
        {
          "lines": [
            {
              "kind": "input",
              "prompt": ">>>",
              "text": "flops.set_printoptions(formatter={'all':lambda x: 'int: '+str(-x)})"
            },
            {
              "kind": "input",
              "prompt": ">>>",
              "text": "x = flops.arange(3)"
            },
            {
              "kind": "input",
              "prompt": ">>>",
              "text": "x"
            },
            {
              "kind": "output",
              "text": "array([int: 0, int: -1, int: -2])"
            },
            {
              "kind": "input",
              "prompt": ">>>",
              "text": "flops.set_printoptions()  # formatter gets reset"
            },
            {
              "kind": "input",
              "prompt": ">>>",
              "text": "x"
            },
            {
              "kind": "output",
              "text": "array([0, 1, 2])"
            }
          ],
          "type": "doctest_block"
        },
        {
          "inline": [
            {
              "kind": "text",
              "text": "To put back the default options, you can use:"
            }
          ],
          "type": "paragraph"
        },
        {
          "lines": [
            {
              "kind": "input",
              "prompt": ">>>",
              "text": "flops.set_printoptions(edgeitems=3, infstr='inf',"
            },
            {
              "kind": "input",
              "prompt": "...",
              "text": "linewidth=75, nanstr='nan', precision=8,"
            },
            {
              "kind": "input",
              "prompt": "...",
              "text": "suppress=False, threshold=1000, formatter=None)"
            }
          ],
          "type": "doctest_block"
        },
        {
          "inline": [
            {
              "kind": "text",
              "text": "Also to temporarily override options, use "
            },
            {
              "kind": "code",
              "text": "printoptions"
            },
            {
              "kind": "text",
              "text": "\nas a context manager:"
            }
          ],
          "type": "paragraph"
        },
        {
          "lines": [
            {
              "kind": "input",
              "prompt": ">>>",
              "text": "with flops.printoptions(precision=2, suppress=True, threshold=5):"
            },
            {
              "kind": "input",
              "prompt": "...",
              "text": "flops.linspace(0, 10, 10)"
            },
            {
              "kind": "output",
              "text": "array([ 0.  ,  1.11,  2.22, ...,  7.78,  8.89, 10.  ], shape=(10,))"
            }
          ],
          "type": "doctest_block"
        }
      ],
      "title": "Examples"
    }
  ],
  "canonical_name": "flopscope.numpy.set_printoptions",
  "canonical_path": "/docs/api/numpy/set-printoptions/",
  "cost_formula": "",
  "cost_formula_latex": "",
  "display_name": "flopscope.numpy.set_printoptions",
  "display_type": "",
  "doc_coverage": {
    "raw_blocks": [],
    "unresolved_references": [],
    "unsupported_directives": []
  },
  "example": {
    "code": "Floating point precision can be set:\n\n>>> import numpy as np\n>>> np.set_printoptions(precision=4)\n>>> np.array([1.123456789])\n[1.1235]\n\nLong arrays can be summarised:\n\n>>> np.set_printoptions(threshold=5)\n>>> np.arange(10)\narray([0, 1, 2, ..., 7, 8, 9], shape=(10,))\n\nSmall results can be suppressed:\n\n>>> eps = np.finfo(float).eps\n>>> x = np.arange(4.)\n>>> x**2 - (x + eps)**2\narray([-4.9304e-32, -4.4409e-16,  0.0000e+00,  0.0000e+00])\n>>> np.set_printoptions(suppress=True)\n>>> x**2 - (x + eps)**2\narray([-0., -0.,  0.,  0.])\n\nA custom formatter can be used to display array elements as desired:\n\n>>> np.set_printoptions(formatter={'all':lambda x: 'int: '+str(-x)})\n>>> x = np.arange(3)\n>>> x\narray([int: 0, int: -1, int: -2])\n>>> np.set_printoptions()  # formatter gets reset\n>>> x\narray([0, 1, 2])\n\nTo put back the default options, you can use:\n\n>>> np.set_printoptions(edgeitems=3, infstr='inf',\n... linewidth=75, nanstr='nan', precision=8,\n... suppress=False, threshold=1000, formatter=None)\n\nAlso to temporarily override options, use `printoptions`\nas a context manager:\n\n>>> with np.printoptions(precision=2, suppress=True, threshold=5):\n...     np.linspace(0, 10, 10)\narray([ 0.  ,  1.11,  2.22, ...,  7.78,  8.89, 10.  ], shape=(10,))",
    "output": "",
    "source": "derived"
  },
  "flopscope_ref": "flopscope.numpy.set_printoptions",
  "flopscope_source_url": "https://github.com/AIcrowd/flopscope/blob/main/.venv/lib/python3.14/site-packages/numpy/_core/arrayprint.py#L113",
  "href": "/docs/api/numpy/set-printoptions/",
  "import_path": "flopscope.numpy.set_printoptions",
  "is_operation_cost_leaf": true,
  "kind": "function",
  "legacy_href": "/docs/api/numpy/set-printoptions/",
  "module": "numpy",
  "name": "set_printoptions",
  "next": null,
  "notes": "",
  "notes_sections": [
    "`formatter` is always reset with a call to `set_printoptions`.",
    "Use `printoptions` as a context manager to set the values temporarily."
  ],
  "numpy_ref": "",
  "operation": null,
  "parameters": [
    {
      "body": [
        "Number of digits of precision for floating point output (default 8).",
        "May be None if `floatmode` is not `fixed`, to print as many digits as",
        "necessary to uniquely specify the value."
      ],
      "name": "precision",
      "type": "int or None, optional"
    },
    {
      "body": [
        "Total number of array elements which trigger summarization",
        "rather than full repr (default 1000).",
        "To always use the full repr without summarization, pass `sys.maxsize`."
      ],
      "name": "threshold",
      "type": "int, optional"
    },
    {
      "body": [
        "Number of array items in summary at beginning and end of",
        "each dimension (default 3)."
      ],
      "name": "edgeitems",
      "type": "int, optional"
    },
    {
      "body": [
        "The number of characters per line for the purpose of inserting",
        "line breaks (default 75)."
      ],
      "name": "linewidth",
      "type": "int, optional"
    },
    {
      "body": [
        "If True, always print floating point numbers using fixed point",
        "notation, in which case numbers equal to zero in the current precision",
        "will print as zero.  If False, then scientific notation is used when",
        "absolute value of the smallest number is < 1e-4 or the ratio of the",
        "maximum absolute value to the minimum is > 1e3. The default is False."
      ],
      "name": "suppress",
      "type": "bool, optional"
    },
    {
      "body": [
        "String representation of floating point not-a-number (default nan)."
      ],
      "name": "nanstr",
      "type": "str, optional"
    },
    {
      "body": [
        "String representation of floating point infinity (default inf)."
      ],
      "name": "infstr",
      "type": "str, optional"
    },
    {
      "body": [
        "Controls printing of the sign of floating-point types. If '+', always",
        "print the sign of positive values. If ' ', always prints a space",
        "(whitespace character) in the sign position of positive values.  If",
        "'-', omit the sign character of positive values. (default '-')",
        "",
        ".. versionchanged:: 2.0",
        "     The sign parameter can now be an integer type, previously",
        "     types were floating-point types."
      ],
      "name": "sign",
      "type": "string, either '-', '+', or ' ', optional"
    },
    {
      "body": [
        "If not None, the keys should indicate the type(s) that the respective",
        "formatting function applies to.  Callables should return a string.",
        "Types that are not specified (by their corresponding keys) are handled",
        "by the default formatters.  Individual types for which a formatter",
        "can be set are:",
        "",
        "- 'bool'",
        "- 'int'",
        "- 'timedelta' : a `flops.timedelta64`",
        "- 'datetime' : a `flops.datetime64`",
        "- 'float'",
        "- 'longfloat' : 128-bit floats",
        "- 'complexfloat'",
        "- 'longcomplexfloat' : composed of two 128-bit floats",
        "- 'numpystr' : types `flops.bytes_` and `flops.str_`",
        "- 'object' : `flops.object_` arrays",
        "",
        "Other keys that can be used to set a group of types at once are:",
        "",
        "- 'all' : sets all types",
        "- 'int_kind' : sets 'int'",
        "- 'float_kind' : sets 'float' and 'longfloat'",
        "- 'complex_kind' : sets 'complexfloat' and 'longcomplexfloat'",
        "- 'str_kind' : sets 'numpystr'"
      ],
      "name": "formatter",
      "type": "dict of callables, optional"
    },
    {
      "body": [
        "Controls the interpretation of the `precision` option for",
        "floating-point types. Can take the following values",
        "(default maxprec_equal):",
        "",
        "* 'fixed': Always print exactly `precision` fractional digits,",
        "        even if this would print more or fewer digits than",
        "        necessary to specify the value uniquely.",
        "* 'unique': Print the minimum number of fractional digits necessary",
        "        to represent each value uniquely. Different elements may",
        "        have a different number of digits. The value of the",
        "        `precision` option is ignored.",
        "* 'maxprec': Print at most `precision` fractional digits, but if",
        "        an element can be uniquely represented with fewer digits",
        "        only print it with that many.",
        "* 'maxprec_equal': Print at most `precision` fractional digits,",
        "        but if every element in the array can be uniquely",
        "        represented with an equal number of fewer digits, use that",
        "        many digits for all elements."
      ],
      "name": "floatmode",
      "type": "str, optional"
    },
    {
      "body": [
        "If set to the string ``'1.13'`` enables 1.13 legacy printing mode. This",
        "approximates numpy 1.13 print output by including a space in the sign",
        "position of floats and different behavior for 0d arrays. This also",
        "enables 1.21 legacy printing mode (described below).",
        "",
        "If set to the string ``'1.21'`` enables 1.21 legacy printing mode. This",
        "approximates numpy 1.21 print output of complex structured dtypes",
        "by not inserting spaces after commas that separate fields and after",
        "colons.",
        "",
        "If set to ``'1.25'`` approximates printing of 1.25 which mainly means",
        "that numeric scalars are printed without their type information, e.g.",
        "as ``3.0`` rather than ``flops.float64(3.0)``.",
        "",
        "If set to ``'2.1'``, shape information is not given when arrays are",
        "summarized (i.e., multiple elements replaced with ``...``).",
        "",
        "If set to `False`, disables legacy mode.",
        "",
        "Unrecognized strings will be ignored with a warning for forward",
        "compatibility.",
        "",
        ".. versionchanged:: 1.22.0",
        ".. versionchanged:: 2.2"
      ],
      "name": "legacy",
      "type": "string or `False`, optional"
    },
    {
      "body": [
        "If set a passed function will be used for generating arrays' repr.",
        "Other options will be ignored."
      ],
      "name": "override_repr: callable, optional",
      "type": ""
    }
  ],
  "previous": null,
  "returns": [],
  "schema_version": 1,
  "see_also": [
    {
      "description": "",
      "description_inline": [],
      "external_url": "https://numpy.org/doc/stable/reference/generated/numpy.get_printoptions.html",
      "href": "",
      "label": "get_printoptions",
      "original_target": "get_printoptions",
      "role": "",
      "target": "get_printoptions",
      "unresolved": false
    },
    {
      "description": "",
      "description_inline": [],
      "external_url": "https://numpy.org/doc/stable/reference/generated/numpy.printoptions.html",
      "href": "",
      "label": "printoptions",
      "original_target": "printoptions",
      "role": "",
      "target": "printoptions",
      "unresolved": false
    },
    {
      "description": "",
      "description_inline": [],
      "external_url": "https://numpy.org/doc/stable/reference/generated/numpy.array2string.html",
      "href": "",
      "label": "array2string",
      "original_target": "array2string",
      "role": "",
      "target": "array2string",
      "unresolved": false
    }
  ],
  "signature": "flopscope.numpy.set_printoptions(precision=None, threshold=None, edgeitems=None, linewidth=None, suppress=None, nanstr=None, infstr=None, formatter=None, sign=None, floatmode=None, *, legacy=None, override_repr=None)",
  "slug": "flopscope-numpy-set-printoptions",
  "summary": "Set printing options.",
  "upstream_source_url": "",
  "weight": 1.0
}
